src/Blockchain.py
src/__init__.py
src/app.py
BlockchainServer-0.1.dist-info/LICENCE
BlockchainServer-0.1.dist-info/METADATA
BlockchainServer-0.1.dist-info/WHEEL
BlockchainServer-0.1.dist-info/top_level.txt
BlockchainServer-0.1.dist-info/RECORD
